{
  "project_info": {
    "project_number": "1025824671597",
    "firebase_url": "https://haji-kadir-restaurant.firebaseio.com",
    "project_id": "haji-kadir-restaurant",
    "storage_bucket": "haji-kadir-restaurant.appspot.com"
  },
  "client": [
    {
      "client_info": {
        "mobilesdk_app_id": "1:1025824671597:android:575344f53e27efd5",
        "android_client_info": {
          "package_name": "winapp.hajikadir.customer"
        }
      },
      "oauth_client": [
        {
          "client_id": "1025824671597-3iipj3l37lkdq2tj2kjed7smg201tri3.apps.googleusercontent.com",
          "client_type": 3
        }
      ],
      "api_key": [
        {
          "current_key": "AIzaSyAXz6yd2Sgf1_fXjH1E-ddmVVmFAztg8MM"
        }
      ],
      "services": {
        "analytics_service": {
          "status": 1
        },
        "appinvite_service": {
          "status": 1,
          "other_platform_oauth_client": []
        },
        "ads_service": {
          "status": 2
        }
      }
    }
  ],
  "configuration_version": "1"
}